.DS_Store
elstargo/__init__.py
elstargo/flow.py
elstargo/myfunctions.py
elstargo-0.0.7.dist-info/LICENSE
elstargo-0.0.7.dist-info/METADATA
elstargo-0.0.7.dist-info/WHEEL
elstargo-0.0.7.dist-info/top_level.txt
elstargo-0.0.7.dist-info/RECORD
