Metadata-Version: 2.1
Name: elstargo
Version: 0.0.7
Summary: FOR THE GREATER GOOD
Home-page: https://github.com/Elstargo00/elstargo_package.git
Author: Elstargo
Author-email: tagam2707@gmail.com
License: UNKNOWN
Platform: UNKNOWN
Classifier: Programming Language :: Python :: 3
Classifier: License :: OSI Approved :: MIT License
Classifier: Operating System :: OS Independent
Requires-Python: >=3.6
